biotite/__init__.py
biotite/copyable.py
biotite/file.py
biotite/setup_ccd.py
biotite/version.py
biotite/visualize.py
biotite/application/__init__.py
biotite/application/application.py
biotite/application/localapp.py
biotite/application/msaapp.py
biotite/application/util.py
biotite/application/webapp.py
biotite/application/autodock/__init__.py
biotite/application/autodock/app.py
biotite/application/blast/__init__.py
biotite/application/blast/alignment.py
biotite/application/blast/webapp.py
biotite/application/clustalo/__init__.py
biotite/application/clustalo/app.py
biotite/application/dssp/__init__.py
biotite/application/dssp/app.py
biotite/application/mafft/__init__.py
biotite/application/mafft/app.py
biotite/application/muscle/__init__.py
biotite/application/muscle/app3.py
biotite/application/muscle/app5.py
biotite/application/sra/__init__.py
biotite/application/sra/app.py
biotite/application/tantan/__init__.py
biotite/application/tantan/app.py
biotite/application/viennarna/__init__.py
biotite/application/viennarna/rnaalifold.py
biotite/application/viennarna/rnafold.py
biotite/application/viennarna/rnaplot.py
biotite/application/viennarna/util.py
biotite/database/__init__.py
biotite/database/error.py
biotite/database/afdb/__init__.py
biotite/database/afdb/download.py
biotite/database/entrez/__init__.py
biotite/database/entrez/check.py
biotite/database/entrez/dbnames.py
biotite/database/entrez/download.py
biotite/database/entrez/key.py
biotite/database/entrez/query.py
biotite/database/pubchem/__init__.py
biotite/database/pubchem/download.py
biotite/database/pubchem/error.py
biotite/database/pubchem/query.py
biotite/database/pubchem/throttle.py
biotite/database/rcsb/__init__.py
biotite/database/rcsb/download.py
biotite/database/rcsb/query.py
biotite/database/uniprot/__init__.py
biotite/database/uniprot/check.py
biotite/database/uniprot/download.py
biotite/database/uniprot/query.py
biotite/interface/__init__.py
biotite/interface/version.py
biotite-1.5.0.dist-info/METADATA
biotite-1.5.0.dist-info/WHEEL
biotite-1.5.0.dist-info/licenses/LICENSE.rst
biotite-1.5.0.dist-info/RECORD
