Metadata-Version: 2.4
Name: biotite
Version: 1.5.0
Summary: A comprehensive library for computational molecular biology
Project-URL: homepage, https://www.biotite-python.org
Project-URL: repository, https://github.com/biotite-dev/biotite
Project-URL: documentation, https://www.biotite-python.org
Author: The Biotite contributors
License-Expression: BSD-3-Clause
License-File: LICENSE.rst
Classifier: Development Status :: 5 - Production/Stable
Classifier: Intended Audience :: Developers
Classifier: Intended Audience :: Science/Research
Classifier: Natural Language :: English
Classifier: Operating System :: MacOS
Classifier: Operating System :: Microsoft :: Windows
Classifier: Operating System :: POSIX :: Linux
Classifier: Programming Language :: Python :: 3
Classifier: Programming Language :: Python :: Implementation :: CPython
Classifier: Topic :: Scientific/Engineering :: Bio-Informatics
Requires-Python: >=3.11
Requires-Dist: biotraj<2.0,>=1.0
Requires-Dist: msgpack>=0.5.6
Requires-Dist: networkx>=2.0
Requires-Dist: numpy>=1.25
Requires-Dist: packaging>=24.0
Requires-Dist: requests>=2.12
Provides-Extra: lint
Requires-Dist: numpydoc==1.8.0; extra == 'lint'
Requires-Dist: ruff==0.9.7; extra == 'lint'
Provides-Extra: test
Requires-Dist: pytest; extra == 'test'
Requires-Dist: pytest-codspeed; extra == 'test'
